{
  "file": "C:\\calculadoras-de-enfermagem\\global-styles.css",
  "totalBlocks": 257,
  "exactDuplicatesCount": 0,
  "exactDuplicates": [],
  "selectorConflictsCount": 6,
  "selectorConflicts": [
    {
      "selector": "header",
      "occurrences": [
        {
          "startLine": 21,
          "endLine": 29,
          "propsKey": "box-shadow:0 2px 4px rgba(0, 0, 0, .1);box-sizing:border-box;left:0;position:fixed;width:100%"
        },
        {
          "startLine": 162,
          "endLine": 168,
          "propsKey": "height:60px;top:36px;z-index:99999"
        }
      ]
    },
    {
      "selector": "@media (max-width:768px)",
      "occurrences": [
        {
          "startLine": 362,
          "endLine": 600,
          "propsKey": null
        },
        {
          "startLine": 1646,
          "endLine": 1678,
          "propsKey": null
        }
      ],
      "note": "mesmas propriedades (duplicado exato para este seletor)"
    },
    {
      "selector": ".desktop-nav ul ul",
      "occurrences": [
        {
          "startLine": 1317,
          "endLine": 1323,
          "propsKey": "box-shadow:0 10px 15px -3px rgba(0, 0, 0, .1), 0 4px 6px -2px rgba(0, 0, 0, .05);flex-direction:column;width:14rem"
        },
        {
          "startLine": 1761,
          "endLine": 1776,
          "propsKey": "background-color:#fff;border-radius:4px;box-shadow:0 4px 8px rgba(0, 0, 0, .1);display:none;flex-direction:column;left:0 !important;min-width:180px;padding:5px 0;position:absolute;right:auto !important;top:100% !important;z-index:1000"
        }
      ]
    },
    {
      "selector": "@font-face",
      "occurrences": [
        {
          "startLine": 1884,
          "endLine": 1891,
          "propsKey": "font-display:swap;font-family:'Inter';font-weight:600;src:url('/fonts/inter/inter-600.woff2') format('woff2')"
        },
        {
          "startLine": 1891,
          "endLine": 1898,
          "propsKey": "font-display:swap;font-family:'Inter';font-weight:700;src:url('/fonts/inter/inter-700.woff2') format('woff2')"
        },
        {
          "startLine": 1909,
          "endLine": 1916,
          "propsKey": "font-display:swap;font-family:'Nunito Sans';font-weight:700;src:url('/fonts/nunito/nunito-700.woff2') format('woff2')"
        },
        {
          "startLine": 1916,
          "endLine": 1923,
          "propsKey": "font-display:swap;font-family:'Nunito Sans';font-weight:900;src:url('/fonts/nunito/nunito-900.woff2') format('woff2')"
        },
        {
          "startLine": 1934,
          "endLine": 1941,
          "propsKey": "font-display:swap;font-family:'Arabic';font-weight:700;src:url('/fonts/arabic/arabic-700.woff2') format('woff2')"
        },
        {
          "startLine": 1953,
          "endLine": 1960,
          "propsKey": "font-display:swap;font-family:'Devanagari';font-weight:700;src:url('/fonts/devanagari/devanagari-700.woff2') format('woff2')"
        },
        {
          "startLine": 1984,
          "endLine": 1991,
          "propsKey": "font-display:swap;font-family:'Japanese';font-weight:700;src:url('/fonts/japanese/japanese-700.woff2') format('woff2')"
        },
        {
          "startLine": 2003,
          "endLine": 2010,
          "propsKey": "font-display:swap;font-family:'Korean';font-weight:700;src:url('/fonts/korean/korean-700.woff2') format('woff2')"
        }
      ]
    },
    {
      "selector": "@media (min-width: 768px)",
      "occurrences": [
        {
          "startLine": 2021,
          "endLine": 2027,
          "propsKey": null
        },
        {
          "startLine": 2053,
          "endLine": 2059,
          "propsKey": null
        }
      ],
      "note": "mesmas propriedades (duplicado exato para este seletor)"
    },
    {
      "selector": "@media (max-width: 768px)",
      "occurrences": [
        {
          "startLine": 2039,
          "endLine": 2045,
          "propsKey": null
        },
        {
          "startLine": 2241,
          "endLine": 2246,
          "propsKey": null
        },
        {
          "startLine": 2252,
          "endLine": 2258,
          "propsKey": null
        }
      ],
      "note": "mesmas propriedades (duplicado exato para este seletor)"
    }
  ]
}